batchform/views.py
batchform/__init__.py
batchform/models.py
batchform/forms.py
batchform/static/batchform/css/batchform.css
batchform/templates/batchform/base.html
batchform/templates/batchform/lines_form.html
batchform/templates/batchform/upload_form.html
batchform/parsers/base.py
batchform/parsers/__init__.py
batchform/parsers/csv.py
django_batchform-0.3.0.dist-info/top_level.txt
django_batchform-0.3.0.dist-info/METADATA
django_batchform-0.3.0.dist-info/WHEEL
django_batchform-0.3.0.dist-info/RECORD
django_batchform-0.3.0.dist-info/metadata.json
django_batchform-0.3.0.dist-info/DESCRIPTION.rst
