Metadata-Version: 2.0
Name: django-batchform
Version: 0.3.0
Summary: Fill a batch of django forms from an uploaded file.
Home-page: http://github.com/rbarrois/django-batchform
Author: Raphaël Barrois
Author-email: raphael.barrois+batchform@polytechnique.org
License: BSD
Download-URL: http://pypi.python.org/pypi/django-batchform/
Keywords: django,form,batch,upload
Platform: UNKNOWN
Classifier: Development Status :: 4 - Beta
Classifier: Intended Audience :: Developers
Classifier: License :: Public Domain
Classifier: Topic :: Software Development :: Libraries :: Python Modules
Classifier: Operating System :: OS Independent
Classifier: Programming Language :: Python
Requires-Dist: Django (>=1.7)
